pythonads/__init__.py
pythonads-0.1.0.dist-info/METADATA
pythonads-0.1.0.dist-info/WHEEL
pythonads-0.1.0.dist-info/RECORD
