Metadata-Version: 2.1
Name: pythonads
Version: 0.1.0
Summary: A sustainable, terminal-based ad network, passing 90% of revenues through to developers.
License: MIT
Author: WillDenby
Author-email: 119456795+WillDenby@users.noreply.github.com
Requires-Python: >=3.7,<4.0
Classifier: License :: OSI Approved :: MIT License
Classifier: Programming Language :: Python :: 3
Classifier: Programming Language :: Python :: 3.7
Classifier: Programming Language :: Python :: 3.8
Classifier: Programming Language :: Python :: 3.9
Classifier: Programming Language :: Python :: 3.10
Classifier: Programming Language :: Python :: 3.11
Classifier: Programming Language :: Python :: 3.12
Requires-Dist: requests (>=2.31.0,<3.0.0)
